[
    {
        "key": "dbln",
        "value": "%7B%2261590914604723%22%3A%22MoPGTgHv%22%2C%2261589400838166%22%3A%22KoNJxdm2%22%7D",
        "domain": "facebook.com",
        "path": "/login/device-based/",
        "hostOnly": false,
        "creation": "2026-07-20T09:55:27.369Z",
        "lastAccessed": "2026-07-20T09:55:27.370Z"
    },
    {
        "key": "sb",
        "value": "moI3alvag14qh9kGVzo2_1BS",
        "domain": "facebook.com",
        "path": "/",
        "hostOnly": false,
        "creation": "2026-07-20T09:55:27.370Z",
        "lastAccessed": "2026-07-20T09:55:27.370Z"
    },
    {
        "key": "ps_l",
        "value": "1",
        "domain": "facebook.com",
        "path": "/",
        "hostOnly": false,
        "creation": "2026-07-20T09:55:27.370Z",
        "lastAccessed": "2026-07-20T09:55:27.370Z"
    },
    {
        "key": "ps_n",
        "value": "1",
        "domain": "facebook.com",
        "path": "/",
        "hostOnly": false,
        "creation": "2026-07-20T09:55:27.370Z",
        "lastAccessed": "2026-07-20T09:55:27.370Z"
    },
    {
        "key": "oo",
        "value": "v1",
        "domain": "facebook.com",
        "path": "/",
        "hostOnly": false,
        "creation": "2026-07-20T09:55:27.370Z",
        "lastAccessed": "2026-07-20T09:55:27.370Z"
    },
    {
        "key": "datr",
        "value": "XbVUaiPAvPRHHCDrHGWeYJUe",
        "domain": "facebook.com",
        "path": "/",
        "hostOnly": false,
        "creation": "2026-07-20T09:55:27.370Z",
        "lastAccessed": "2026-07-20T09:55:27.370Z"
    },
    {
        "key": "dpr",
        "value": "3",
        "domain": "facebook.com",
        "path": "/",
        "hostOnly": false,
        "creation": "2026-07-20T09:55:27.370Z",
        "lastAccessed": "2026-07-20T09:55:27.370Z"
    },
    {
        "key": "pas",
        "value": "61590914604723%3AJGlcXXTfpV%2C61589400838166%3AJSgI2Pu4to%2C61590816660009%3AOJp1OxumAd",
        "domain": "facebook.com",
        "path": "/",
        "hostOnly": false,
        "creation": "2026-07-20T09:55:27.370Z",
        "lastAccessed": "2026-07-20T09:55:27.370Z"
    },
    {
        "key": "locale",
        "value": "en_US",
        "domain": "facebook.com",
        "path": "/",
        "hostOnly": false,
        "creation": "2026-07-20T09:55:27.370Z",
        "lastAccessed": "2026-07-20T09:55:27.370Z"
    },
    {
        "key": "vpd",
        "value": "v1%3B640x360x3",
        "domain": "facebook.com",
        "path": "/",
        "hostOnly": false,
        "creation": "2026-07-20T09:55:27.370Z",
        "lastAccessed": "2026-07-20T09:55:27.370Z"
    },
    {
        "key": "m_pixel_ratio",
        "value": "3",
        "domain": "facebook.com",
        "path": "/",
        "hostOnly": false,
        "creation": "2026-07-20T09:55:27.370Z",
        "lastAccessed": "2026-07-20T09:55:27.370Z"
    },
    {
        "key": "wd",
        "value": "360x820",
        "domain": "facebook.com",
        "path": "/",
        "hostOnly": false,
        "creation": "2026-07-20T09:55:27.370Z",
        "lastAccessed": "2026-07-20T09:55:27.370Z"
    },
    {
        "key": "c_user",
        "value": "61589400838166",
        "domain": "facebook.com",
        "path": "/",
        "hostOnly": false,
        "creation": "2026-07-20T09:55:27.370Z",
        "lastAccessed": "2026-07-20T09:55:27.370Z"
    },
    {
        "key": "xs",
        "value": "2%3AQMvcOxfZzB6L4Q%3A2%3A1784541314%3A-1%3A-1",
        "domain": "facebook.com",
        "path": "/",
        "hostOnly": false,
        "creation": "2026-07-20T09:55:27.370Z",
        "lastAccessed": "2026-07-20T09:55:27.370Z"
    },
    {
        "key": "fr",
        "value": "0p5oLyBiAJXIQTbKH.AWchRGPFqOgi2lkJNwFo-t1Ixv-G3Jygttw2ckXjXBCXeufClYU.BqTIDc..AAA.0.0.BqXfCH.AWdCqObNo28cyEOeWy7ZWByIbYo",
        "domain": "facebook.com",
        "path": "/",
        "hostOnly": false,
        "creation": "2026-07-20T09:55:27.370Z",
        "lastAccessed": "2026-07-20T09:55:27.370Z"
    },
    {
        "key": "wl_cbv",
        "value": "v2%3Bclient_version%3A3222%3Btimestamp%3A1784541319",
        "domain": "facebook.com",
        "path": "/",
        "hostOnly": false,
        "creation": "2026-07-20T09:55:27.370Z",
        "lastAccessed": "2026-07-20T09:55:27.370Z"
    },
    {
        "key": "fbl_st",
        "value": "101727760%3BT%3A29742355",
        "domain": "facebook.com",
        "path": "/",
        "hostOnly": false,
        "creation": "2026-07-20T09:55:27.370Z",
        "lastAccessed": "2026-07-20T09:55:27.370Z"
    }
]
